pickLayer/__init__.py
pickLayer/metadata.txt
pickLayer/plugin.py
pickLayer/core/__init__.py
pickLayer/core/identifygeometry.py
pickLayer/core/picklayer.py
pickLayer/core/set_active_layer_tool.py
pickLayer/definitions/__init__.py
pickLayer/definitions/settings.py
pickLayer/resources/i18n/fi.qm
pickLayer/resources/i18n/fi.ts
pickLayer/resources/icons/copyIcon.png
pickLayer/resources/icons/copyPaste.png
pickLayer/resources/icons/customAction.png
pickLayer/resources/icons/dataSource.png
pickLayer/resources/icons/mActionOpenTable.png
pickLayer/resources/icons/mActionPropertyItem.png
pickLayer/resources/icons/mIconEditable.png
pickLayer/resources/icons/mIconEditableEdits.png
pickLayer/resources/icons/mSetCurrentLayer.png
pickLayer/resources/icons/makeValidIcon.png
pickLayer/resources/icons/mergeIcon.png
pickLayer/resources/icons/off.png
pickLayer/resources/icons/pasteAttributes.png
pickLayer/resources/icons/pasteGeometry.png
pickLayer/resources/icons/pasteIcon.png
pickLayer/resources/icons/pick_layer.svg
pickLayer/resources/icons/pick_layer_lite.svg
pickLayer/resources/icons/settings.svg
pickLayer/resources/icons/snapIcon.png
pickLayer/resources/icons/subtractIcon.png
pickLayer/resources/icons/zoomToFeature.png
pickLayer/resources/icons/zoomToLayer.png
pickLayer/resources/ui/settings_dialog.ui
pickLayer/resources/ui/snappingdialog.ui
pickLayer/resources/ui/ui_changeDSDialog.ui
pickLayer/resources/ui/ui_picksnapdialog.ui
pickLayer/ui/__init__.py
pickLayer/ui/settings_dialog.py
pickLayer-3.9.13.dist-info/LICENSE
pickLayer-3.9.13.dist-info/METADATA
pickLayer-3.9.13.dist-info/WHEEL
pickLayer-3.9.13.dist-info/entry_points.txt
pickLayer-3.9.13.dist-info/top_level.txt
pickLayer-3.9.13.dist-info/RECORD
