Metadata-Version: 2.1
Name: pickLayer
Version: 3.9.13
Summary: QGIS plugin for setting layer properties and options straight from map canvas and for activating layer by clicking features on map.
Home-page: https://github.com/nlsfi/pickLayer
Author: National Land Survey of Finland
Author-email: os@nls.fi
License: GNU GPL v3.0
Project-URL: Changelog, https://github.com/nlsfi/pickLayer/blob/main/CHANGELOG.md
Keywords: qgis
Classifier: Development Status :: 3 - Alpha
Classifier: License :: OSI Approved :: GNU General Public License v3 (GPLv3)
Classifier: Operating System :: OS Independent
Classifier: Programming Language :: Python :: 3 :: Only
Classifier: Programming Language :: Python :: Implementation :: CPython
Classifier: Topic :: Software Development :: Libraries
Classifier: Typing :: Typed
License-File: LICENSE
Requires-Dist: qgis_plugin_tools>=0.4.0
